{
  "bodyMaterials1": [
    {
      "id": 0,
      "name": "ЛДСП Lamarty Древесные 16 мм + 0,4 мм кромкой",
      "price": 12,
      "union": "m2"
    },
    {
      "id": 0,
      "name": "ЛДСП Lamarty Древесные 16 мм + 2 мм кромкой",
      "price": 12,
      "union": "m2"
    },
    {
      "id": 0,
      "name": "ЛДСП Lamarty Древесные 26 мм + 0,4 мм кромкой",
      "price": 12,
      "union": "m2"
    }
  ],
  "calcGroups": [
    {
      "id": 0,
      "name": "Корпус"
    },
    {
      "id": 1,
      "name": "ХДФ"
    },
    {
      "id": 2,
      "name": "Зеркала/стекла"
    }
  ]
}
